df2obs/base.py
df2obs-0.1.0.dist-info/METADATA
df2obs-0.1.0.dist-info/WHEEL
df2obs-0.1.0.dist-info/top_level.txt
df2obs-0.1.0.dist-info/RECORD
