Metadata-Version: 2.1
Name: df2obs
Version: 0.1.0
Summary: A tool to convert DataFrame to a list of objects of some class or vice versa
Home-page: https://github.com/ldmax/df2obs.git
Author: Dan Li
Author-email: lidanmax@163.com
License: MIT
Platform: UNKNOWN
Classifier: License :: OSI Approved :: MIT License
Classifier: Programming Language :: Python :: 3
Classifier: Programming Language :: Python :: 3.7
Requires-Dist: pandas
